CHANGES.rst
MANIFEST.in
README.rst
setup.cfg
setup.py
site/CNAME
site/favicon.ico
site/index.html
site/styles.css
test/actions.t
test/fin.t
test/format.t
test/interrupt.t
test/note.t
test/on.t
test/status.t
test/tag.t
test/timing.t
ti/__init__.py
ti.egg-info/PKG-INFO
ti.egg-info/SOURCES.txt
ti.egg-info/dependency_links.txt
ti.egg-info/entry_points.txt
ti.egg-info/requires.txt
ti.egg-info/top_level.txt