Metadata-Version: 1.0
Name: ti
Version: 0.1.0
Summary: A silly simple time tracker
Home-page: http://ti.sharats.me/
Author: Shrikant Sharat
Author-email: shrikantsharat.k@gmail.com
License: UNKNOWN
Platform: UNKNOWN
